[{"route":"/"},{"route":"/about"},{"route":"/projects"},{"route":"/blog"},{"route":"/blog/___UNPUBLISHED___l5dpw9nv_MovSlmVJIXBxl73vf8W95qgmffEKSTa8","title":"2022-07-09-blog","description":"blog description","published":false,"slug":"___UNPUBLISHED___l5dpw9nv_MovSlmVJIXBxl73vf8W95qgmffEKSTa8","sourceFile":"2022-07-09-blog.md"},{"route":"/blog/blog-post-1","title":"Blog Post 1","description":"My first blog post","published":true,"sourceFile":"blog-post-1.md"},{"route":"/blog/blog-post-2","title":"Blog Post 2","description":"blog description","published":true,"sourceFile":"blog-post-2.md"},{"route":"/blog/blog-post-3","title":"Blog Post 3","description":"blog description","published":true,"sourceFile":"blog-post-3.md"}]